deep_orderbook/__init__.py
deep_orderbook/__main__.py
deep_orderbook/live_image.py
deep_orderbook/recorder.py
deep_orderbook/replayer.py
deep_orderbook/shapper.py
deep_orderbook/testasync.py
deep_orderbook-0.3.0.dist-info/METADATA
deep_orderbook-0.3.0.dist-info/WHEEL
deep_orderbook-0.3.0.dist-info/entry_points.txt
deep_orderbook-0.3.0.dist-info/top_level.txt
deep_orderbook-0.3.0.dist-info/RECORD
