Metadata-Version: 2.1
Name: deep-orderbook
Version: 0.3.0
Summary: Transforms orders books in temporally and spatially local-correlated images.
Home-page: https://github.com/gQuantCoder/deep_orderbook
Author: gQuantCoder
Author-email: gquantcoder@gmail.com
License: UNKNOWN
Platform: UNKNOWN
Requires-Python: >=3.7.4
Requires-Dist: tqdm
Requires-Dist: aioitertools
Requires-Dist: aiofiles
Requires-Dist: websockets
Requires-Dist: matplotlib
